[
  {
    "id": "R_XYZ789",
    "cabana_id": "C001",
    "huesped": {
      "nombre": "Laura Gómez",
      "email": "laura@example.com",
      "telefono": "1122334455"
    },
    "fecha_entrada": "2025-02-01",
    "fecha_salida": "2025-02-08",
    "cantidad_personas": 3,
    "fecha_creacion": "2024-11-14T10:00:00Z",
    "estado": "confirmada"
  },
  {
    "id": "R_ABC123",
    "cabana_id": "C002",
    "huesped": {
      "nombre": "Pedro Ruiz",
      "email": "pedro@example.com",
      "telefono": "9876543210"
    },
    "fecha_entrada": "2025-03-10",
    "fecha_salida": "2025-03-15",
    "cantidad_personas": 2,
    "fecha_creacion": "2024-11-14T11:45:00Z",
    "estado": "confirmada"
  },
  {
    "id": "R_a8f276ac-700e-4851-994c-f4b15047fa74",
    "cabana_id": "5",
    "huesped": {
      "nombre": "Pablo Navarro",
      "email": "crgespartano@gmail.com",
      "telefono": "+54 9 223 4545785"
    },
    "fecha_entrada": "2025-12-12",
    "fecha_salida": "2025-12-18",
    "cantidad_personas": 6,
    "fecha_creacion": "2025-11-24T22:54:44.695Z",
    "estado": "confirmada"
  }
]